sms_message_local/Message.py
sms_message_local/__init__.py
sms_message_local-0.0.1.dist-info/METADATA
sms_message_local-0.0.1.dist-info/WHEEL
sms_message_local-0.0.1.dist-info/top_level.txt
sms_message_local-0.0.1.dist-info/RECORD
