Metadata-Version: 2.1
Name: sms-message-local
Version: 0.0.1
Home-page: https://github.com/circles-zone/sms-message-local-python-package
Author: Circles
Author-email: info@circles.life
Classifier: Programming Language :: Python :: 3
Classifier: License :: Other/Proprietary License
Classifier: Operating System :: OS Independent
